yfscraper/__init__.py
yfscraper/parser.py
yfscraper-0.1.1.dist-info/DESCRIPTION.rst
yfscraper-0.1.1.dist-info/METADATA
yfscraper-0.1.1.dist-info/RECORD
yfscraper-0.1.1.dist-info/WHEEL
yfscraper-0.1.1.dist-info/metadata.json
yfscraper-0.1.1.dist-info/top_level.txt
