Metadata-Version: 2.0
Name: yfscraper
Version: 0.1.1
Summary: yahoo finance japan parser
Home-page: https://github.com/lucidfrontier45/yfscraper
Author: Shiqiao Du
Author-email: lucidfrontier.45@gmail.com
License: UNKNOWN
Platform: UNKNOWN
Requires-Dist: bs4
Requires-Dist: requests
